[
    {
        "type": "Grocery",
        "name": "Golden Circle Factory Outlet, Capalaba",
        "address": "Shop 16/200 Old Cleveland Rd, Capalaba QLD 4157",
        "saturdayOpenHrs": "8:30 am-4 pm",
        "sundayOpenHrs": "9 am-5 pm",
        "mondayOpenHrs": "9 am-5 pm",
        "tuesdayOpenHrs": "9 am-5 pm",
        "wednesdaydayOpenHrs": "9 am-5 pm",
        "thrusdayOpenHrs": "9 am-5 pm",
        "fridayOpenHrs": "9 am-5 pm",
        "phone": "(07) 3245 2477",
        "google-reviews": 4.5,
        "website": "https://www.gcfo.com.au/",
        "keywords": ["grocery"],
        "latNLong": [-27.516813491490236, 153.1991478976023]
    },
    {
        "type": "Grocery",
        "name": "Fresh And Save, Morayfield",
        "address": "70/86 Michael Ave, Morayfield QLD 4506",
        "saturdayOpenHrs": "7 am-9 pm",
        "sundayOpenHrs": "7 am-9 pm",
        "mondayOpenHrs": "7 am-9 pm",
        "tuesdayOpenHrs": "7 am-9 pm",
        "wednesdaydayOpenHrs": "7 am-9 pm",
        "thrusdayOpenHrs": "7 am-9 pm",
        "fridayOpenHrs": "7 am-9 pm",
        "phone": "(07) 5432 3555",
        "google-reviews": 4.5,
        "website": "https://www.freshandsave.com.au/",
        "keywords": ["grocery"],
        "latNLong": [-27.10070853275601, 152.94587786790046]
    },
    {
        "type": "Grocery",
        "name": "Fresh And Save, Deagon",
        "address": "75 Braun St, Deagon QLD 4017",
        "saturdayOpenHrs": "6 am-8 pm",
        "sundayOpenHrs": "6 am-8 pm",
        "mondayOpenHrs": "6 am-8 pm",
        "tuesdayOpenHrs": "6 am-8 pm",
        "wednesdaydayOpenHrs": "6 am-8 pm",
        "thrusdayOpenHrs": "6 am-8 pm",
        "fridayOpenHrs": "6 am-8 pm",
        "phone": "(07) 3269 0387",
        "google-reviews": 4.5,
        "website": "https://www.freshandsave.com.au/",
        "keywords": ["grocery"],
        "latNLong": [-27.330376273805786, 153.05726049589373]
    },
    {
        "type": "Grocery",
        "name": "Fresh And Save, Richlands",
        "address": "144 Pine Rd, Richlands QLD 4077",
        "saturdayOpenHrs": "7 am-9 pm",
        "sundayOpenHrs": "7 am-9 pm",
        "mondayOpenHrs": "7 am-9 pm",
        "tuesdayOpenHrs": "7 am-9 pm",
        "wednesdaydayOpenHrs": "7 am-9 pm",
        "thrusdayOpenHrs": "7 am-9 pm",
        "fridayOpenHrs": "7 am-9 pm",
        "phone": "(07) 3879 5906",
        "google-reviews": 4.5,
        "website": "https://www.freshandsave.com.au/",
        "keywords": ["grocery"],
        "latNLong": [-27.58941967785702, 152.95153871589764]
    },
    {
        "type": "Grocery",
        "name": "Fresh And Save, Eagleby",
        "address": "River Hills Rd, Eagleby QLD 4207",
        "saturdayOpenHrs": "6 am-9 pm",
        "sundayOpenHrs": "6 am-9 pm",
        "mondayOpenHrs": "6 am-9 pm",
        "tuesdayOpenHrs": "6 am-9 pm",
        "wednesdaydayOpenHrs": "6 am-9 pm",
        "thrusdayOpenHrs": "6 am-9 pm",
        "fridayOpenHrs": "6 am-9 pm",
        "phone": "(07) 3287 2444",
        "google-reviews": 4,
        "website": "https://www.freshandsave.com.au/",
        "keywords": ["grocery"],
        "latNLong": [-27.693242754620822, 153.21423331159446]
    },
    {
        "type": "Grocery",
        "name": "Tribe of Judah Care Services",
        "address": "101 Park Rd, Slacks Creek QLD 4127",
        "saturdayOpenHrs": "7:30 am-5 pm",
        "sundayOpenHrs": "8 am-4 pm",
        "mondayOpenHrs": "8 am-5:30 pm",
        "tuesdayOpenHrs": "8 am-5:30 pm",
        "wednesdaydayOpenHrs": "8 am-5:30 pm",
        "thrusdayOpenHrs": "8 am-5:30 pm",
        "fridayOpenHrs": "8 am-5:30 pm",
        "phone": "(07) 3290 3610",
        "google-reviews": 4.5,
        "website": "https://m.facebook.com/tribecare/",
        "keywords": ["grocery"],
        "latNLong": [-27.626874814245603, 153.12760843616334]
    },
    {
        "type": "Grocery",
        "name": "Drakes, Rochedale",
        "address": "549 Underwood Rd, Rochedale QLD 4123",
        "saturdayOpenHrs": "7 am-9 pm",
        "sundayOpenHrs": "9 am-6 pm",
        "mondayOpenHrs": "7 am-9 pm",
        "tuesdayOpenHrs": "7 am-9 pm",
        "wednesdaydayOpenHrs": "7 am-9 pm",
        "thrusdayOpenHrs": "7 am-9 pm",
        "fridayOpenHrs": "7 am-9 pm",
        "phone": "(07) 3714 7000",
        "google-reviews": 4.5,
        "website": "https://drakes.com.au/",
        "keywords": ["grocery"],
        "latNLong": [-27.596777126981348, 153.12490739675158]
    },
    {
        "type": "Grocery",
        "name": "Drakes, McDowall",
        "address": "Shop 467/109 Beckett Rd, McDowall QLD 4053",
        "saturdayOpenHrs": "7 am-9 pm",
        "sundayOpenHrs": "7 am-9 pm",
        "mondayOpenHrs": "7 am-9 pm",
        "tuesdayOpenHrs": "7 am-9 pm",
        "wednesdaydayOpenHrs": "7 am-9 pm",
        "thrusdayOpenHrs": "7 am-9 pm",
        "fridayOpenHrs": "7 am-9 pm",
        "phone": "(07) 3550 6000",
        "google-reviews": 4.5,
        "website": "https://drakes.com.au/",
        "keywords": ["grocery"],
        "latNLong": [-27.379938930258227, 152.9901134346201]
    },
    {
        "type": "Grocery",
        "name": "Drakes, Regents Park",
        "address": "Cnr Estramina Road &, Beaudesert Rd, Regents Park QLD 4118",
        "saturdayOpenHrs": "6 am-9 pm",
        "sundayOpenHrs": "6 am-9 pm",
        "mondayOpenHrs": "6 am-9 pm",
        "tuesdayOpenHrs": "6 am-9 pm",
        "wednesdaydayOpenHrs": "6 am-9 pm",
        "thrusdayOpenHrs": "6 am-9 pm",
        "fridayOpenHrs": "6 am-9 pm",
        "phone": "(07) 3386 8500",
        "google-reviews": 4,
        "website": "https://drakes.com.au/",
        "keywords": ["grocery"],
        "latNLong": [-27.665499833710754, 153.0345826390836]
    },
    {
        "type": "Grocery",
        "name": "Drakes, North Lakes",
        "address": "71 Astley Parade, North Lakes QLD 4509",
        "saturdayOpenHrs": "7 am-9 pm",
        "sundayOpenHrs": "7 am-9 pm",
        "mondayOpenHrs": "7 am-9 pm",
        "tuesdayOpenHrs": "7 am-9 pm",
        "wednesdaydayOpenHrs": "7 am-9 pm",
        "thrusdayOpenHrs": "7 am-9 pm",
        "fridayOpenHrs": "7 am-9 pm",
        "phone": "(07) 3490 1000",
        "google-reviews": 4.5,
        "website": "https://drakes.com.au/",
        "keywords": ["grocery"],
        "latNLong": [-27.22141530857835, 153.00146265440983]
    },
    {
        "type": "Grocery",
        "name": "Drakes, Parkinson",
        "address": "Cnr Nottingham Road & Algester Road, Parkinson QLD 4115",
        "saturdayOpenHrs": "7 am-9 pm",
        "sundayOpenHrs": "9 am-6 pm",
        "mondayOpenHrs": "7 am-9 pm",
        "tuesdayOpenHrs": "7 am-9 pm",
        "wednesdaydayOpenHrs": "7 am-9 pm",
        "thrusdayOpenHrs": "7 am-9 pm",
        "fridayOpenHrs": "7 am-9 pm",
        "phone": "(07) 3711 0000",
        "google-reviews": 4.5,
        "website": "https://drakes.com.au/",
        "keywords": ["grocery"],
        "latNLong": [-27.628592743530778, 153.02766525442306]
    },
    {
        "type": "Grocery",
        "name": "Drakes, Ashmore",
        "address": "Cnr Currumburra Road &, Southport Nerang Rd, Ashmore QLD 4214",
        "saturdayOpenHrs": "7 am-9 pm",
        "sundayOpenHrs": "9 am-6 pm",
        "mondayOpenHrs": "7 am-9 pm",
        "tuesdayOpenHrs": "7 am-9 pm",
        "wednesdaydayOpenHrs": "7 am-9 pm",
        "thrusdayOpenHrs": "7 am-9 pm",
        "fridayOpenHrs": "7 am-9 pm",
        "phone": "(07) 5585 6000",
        "google-reviews": 4,
        "website": "https://drakes.com.au/",
        "keywords": ["grocery"],
        "latNLong": [-27.977614427626374, 153.38070109676406]
    },
    {
        "type": "Grocery",
        "name": "Drakes, Winston Glades",
        "address": "259 Ash St, Yamanto QLD 4305",
        "saturdayOpenHrs": "7 am-9 pm",
        "sundayOpenHrs": "9 am-6 pm",
        "mondayOpenHrs": "7 am-9 pm",
        "tuesdayOpenHrs": "7 am-9 pm",
        "wednesdaydayOpenHrs": "7 am-9 pm",
        "thrusdayOpenHrs": "7 am-9 pm",
        "fridayOpenHrs": "7 am-9 pm",
        "phone": "(07) 3436 4900",
        "google-reviews": 4.5,
        "website": "https://drakes.com.au/",
        "keywords": ["grocery"],
        "latNLong": [-27.652402154108593, 152.76467872267395]
    },
    {
        "type": "Grocery",
        "name": "Lighthouse Care, Loganholme",
        "address": "17 Monte Khoury Dr, Loganholme QLD 4129",
        "saturdayOpenHrs": "9 am-12 pm",
        "sundayOpenHrs": "Closed",
        "mondayOpenHrs": "9 am-5 pm",
        "tuesdayOpenHrs": "9 am-5 pm",
        "wednesdaydayOpenHrs": "9 am-5 pm",
        "thrusdayOpenHrs": "9 am-5 pm",
        "fridayOpenHrs": "9 am-5 pm",
        "phone": "(07) 3806 0639",
        "google-reviews": 4.5,
        "website": "https://lighthousecare.org.au/",
        "keywords": ["grocery"],
        "latNLong": [-27.68454990435829, 153.19317243617508]
    },
    {
        "type": "Grocery",
        "name": "Lighthouse Care, Hillcrest",
        "address": "1/16 Central Ct, Hillcrest QLD 4118",
        "saturdayOpenHrs": "9 am-12 pm",
        "sundayOpenHrs": "Closed",
        "mondayOpenHrs": "9 am-5 pm",
        "tuesdayOpenHrs": "9 am-5 pm",
        "wednesdaydayOpenHrs": "9 am-5 pm",
        "thrusdayOpenHrs": "9 am-5 pm",
        "fridayOpenHrs": "9 am-5 pm",
        "phone": "(07) 3806 0639",
        "google-reviews": 4.5,
        "website": "https://lighthousecare.org.au/",
        "keywords": ["grocery"],
        "latNLong": [-27.661594604183854, 153.03600588325943]
    },
    {
        "type": "Grocery",
        "name": "T-Bones Fresh Food Market",
        "address": "605 Robinson Rd W, Aspley QLD 4034",
        "saturdayOpenHrs": "7 am-9 pm",
        "sundayOpenHrs": "8 am-6 pm",
        "mondayOpenHrs": "7 am-9 pm",
        "tuesdayOpenHrs": "7 am-9 pm",
        "wednesdaydayOpenHrs": "7 am-9 pm",
        "thrusdayOpenHrs": "7 am-9 pm",
        "fridayOpenHrs": "7 am-9 pm",
        "phone": "(07) 3863 1100",
        "google-reviews": 4,
        "website": "https://www.tbonesfresh.com.au/",
        "keywords": ["grocery"],
        "latNLong": [-27.36404745163986, 153.02409379674413]
    },    {
        "type": "Grocery",
        "name": "Golden Circle Factory Outlet, Morayfield",
        "address": "Shop 3/343 Morayfield Rd, Morayfield QLD 4506",
        "saturdayOpenHrs": "8:30 am-4 pm",
        "sundayOpenHrs": "9 am-5 pm",
        "mondayOpenHrs": "9 am-5 pm",
        "tuesdayOpenHrs": "9 am-5 pm",
        "wednesdaydayOpenHrs": "9 am-5 pm",
        "thrusdayOpenHrs": "9 am-5 pm",
        "fridayOpenHrs": "9 am-5 pm",
        "phone": "(07) 5499 0938",
        "google-reviews": 4.5,
        "website": "https://www.gcfo.com.au/",
        "keywords": ["grocery"],
        "latNLong": [-27.117677322771932, 152.95574649373154]

    },
    {
        "type": "Grocery",
        "name": "Fresh And Save, Morayfield",
        "address": "70/86 Michael Ave, Morayfield QLD 4506",
        "saturdayOpenHrs": "7 am-9 pm",
        "sundayOpenHrs": "7 am-9 pm",
        "mondayOpenHrs": "7 am-9 pm",
        "tuesdayOpenHrs": "7 am-9 pm",
        "wednesdaydayOpenHrs": "7 am-9 pm",
        "thrusdayOpenHrs": "7 am-9 pm",
        "fridayOpenHrs": "7 am-9 pm",
        "phone": "(07) 5432 3555",
        "google-reviews": 4.5,
        "website": "https://www.freshandsave.com.au/",
        "keywords": ["grocery"],
        "latNLong": [-27.10070853275601, 152.94587786790046]
    },
    {
        "type": "Grocery",
        "name": "Fresh And Save, Deagon",
        "address": "75 Braun St, Deagon QLD 4017",
        "saturdayOpenHrs": "6 am-8 pm",
        "sundayOpenHrs": "6 am-8 pm",
        "mondayOpenHrs": "6 am-8 pm",
        "tuesdayOpenHrs": "6 am-8 pm",
        "wednesdaydayOpenHrs": "6 am-8 pm",
        "thrusdayOpenHrs": "6 am-8 pm",
        "fridayOpenHrs": "6 am-8 pm",
        "phone": "(07) 3269 0387",
        "google-reviews": 4.5,
        "website": "https://www.freshandsave.com.au/",
        "keywords": ["grocery"],
        "latNLong": [-27.330376273805786, 153.05726049589373]
    },
    {
        "type": "Produce",
        "name": "Coco's, Annerley",
        "address": "310 Ipswich Rd, Annerley QLD 4103",
        "saturdayOpenHrs": "24 hours",
        "sundayOpenHrs": "24 hours",
        "mondayOpenHrs": "24 hours",
        "tuesdayOpenHrs": "24 hours",
        "wednesdaydayOpenHrs": "24 hours",
        "thrusdayOpenHrs": "24 hours",
        "fridayOpenHrs": "24 hours",
        "phone": "(07) 3891 2292",
        "google-reviews": 4,
        "website": "https://www.samcocotrading.com.au/",
        "keywords": ["fruit", "vegetables"],
        "latNLong": [-27.50185519547979, 153.03500336058482]
    },
    {
        "type": "Produce",
        "name": "Pinelands Fruit World",
        "address": "Pinelands Plaza Shopping Ctr, Shop/10 Pinelands Rd, Sunnybank Hills QLD 4109",
        "saturdayOpenHrs": "24 hours",
        "sundayOpenHrs": "24 hours",
        "mondayOpenHrs": "24 hours",
        "tuesdayOpenHrs": "24 hours",
        "wednesdaydayOpenHrs": "24 hours",
        "thrusdayOpenHrs": "24 hours",
        "fridayOpenHrs": "24 hours",
        "phone": "0731941870",
        "google-reviews": 4,
        "website": "http://pinelands-world.edan.io/",
        "keywords": ["fruit", "vegetables"],
        "latNLong": [-27.588547524620886, 153.06132876998524]
    },
    {
        "type": "Produce",
        "name": "Clint's Farm Fresh Produce",
        "address": "11 Pine Mountain Rd, North Ipswich QLD 4305",
        "saturdayOpenHrs": "8 am-4 pm",
        "sundayOpenHrs": "8 am-3 pm",
        "mondayOpenHrs": "Closed",
        "tuesdayOpenHrs": "Closed",
        "wednesdaydayOpenHrs": "Closed",
        "thrusdayOpenHrs": "Closed",
        "fridayOpenHrs": "8 am-5:30 pm",
        "phone": "NA",
        "google-reviews": 4.5,
        "website": "https://www.facebook.com/ClintsFarmFreshProduce/",
        "keywords": ["fruit", "vegetables"],
        "latNLong": [-27.59511274263985, 152.76134276976273]
    },
    {
        "type": "Produce",
        "name": "Yuen's Farmers Market, Underwood",
        "address": "Shop 11, 11/21 Kingston Rd, Underwood QLD 4119",
        "saturdayOpenHrs": "24 hours",
        "sundayOpenHrs": "24 hours",
        "mondayOpenHrs": "24 hours",
        "tuesdayOpenHrs": "24 hours",
        "wednesdaydayOpenHrs": "24 hours",
        "thrusdayOpenHrs": "24 hours",
        "fridayOpenHrs": "24 hours",
        "phone": "NA",
        "google-reviews": 4,
        "website": "https://yuensfarmersmarket.com.au/",
        "keywords": ["fruit", "vegetables"],
        "latNLong": [-27.608899433187002, 153.11017169675213]
    },
    {
        "type": "Produce",
        "name": "Yuen's Farmers Market, Waterford West",
        "address": "Shop 1, Waterford Plaza, 917 Kingston Rd, Waterford West QLD 4133",
        "saturdayOpenHrs": "6 am-7 pm",
        "sundayOpenHrs": "6 am-7 pm",
        "mondayOpenHrs": "6 am-7 pm",
        "tuesdayOpenHrs": "6 am-7 pm",
        "wednesdaydayOpenHrs": "6 am-7 pm",
        "thrusdayOpenHrs": "6 am-7 pm",
        "fridayOpenHrs": "6 am-7 pm",
        "phone": "(07) 3805 3147",
        "google-reviews": 4,
        "website": "https://yuensfarmersmarket.com.au/",
        "keywords": ["fruit", "vegetables"],
        "latNLong": [-27.69220327736614, 153.13523385442525]
    },
    {
        "type": "Produce",
        "name": "Wynnum Fruit Basket",
        "address": "Shop 43 - 44 Wynnum Plaza Shopping Centre, 2021 Wynnum Rd, Wynnum West QLD 4178",
        "saturdayOpenHrs": "7 am-7 pm",
        "sundayOpenHrs": "9 am-6 pm",
        "mondayOpenHrs": "6 am-7 pm",
        "tuesdayOpenHrs": "7 am-7 pm",
        "wednesdaydayOpenHrs": "7 am-7 pm",
        "thrusdayOpenHrs": "6 am-9 pm",
        "fridayOpenHrs": "7 am-7 pm",
        "phone": "(07) 3157 3977",
        "google-reviews": 3,
        "website": "https://www.facebook.com/Wynnumfruitbasket/",
        "keywords": ["fruit", "vegetables"],
        "latNLong": [-27.457778093118296, 153.15429368465738]
    },
    {
        "type": "Produce",
        "name": "Bellas Fruit Market",
        "address": "218 Padstow Rd, Eight Mile Plains QLD 4113",
        "saturdayOpenHrs": "24 hours",
        "sundayOpenHrs": "24 hours",
        "mondayOpenHrs": "24 hours",
        "tuesdayOpenHrs": "24 hours",
        "wednesdaydayOpenHrs": "24 hours",
        "thrusdayOpenHrs": "24 hours",
        "fridayOpenHrs": "24 hours",
        "phone": "(07) 3341 1095",
        "google-reviews": 4,
        "website": "https://www.facebook.com/bellasfruitmarket/",
        "keywords": ["fruit", "vegetables"],
        "latNLong": [-27.57393541019538, 153.08758677671307]
    },
    {
        "type": "Produce",
        "name": "Rock 'N' Roll Marketplace",
        "address": "500 Logan Rd, Greenslopes QLD 4120",
        "saturdayOpenHrs": "6 am-5 pm",
        "sundayOpenHrs": "6 am-5 pm",
        "mondayOpenHrs": "6 am-6 pm",
        "tuesdayOpenHrs": "6 am-6 pm",
        "wednesdaydayOpenHrs": "6 am-6 pm",
        "thrusdayOpenHrs": "6 am-6 pm",
        "fridayOpenHrs": "6 am-6 pm",
        "phone": "(07) 3847 1093",
        "google-reviews": 4.5,
        "website": "https://www.instagram.com/rocknrollmarketplace/",
        "keywords": ["fruit", "vegetables"],
        "latNLong": [-27.50430267297861, 153.04800745397543]
    },
    {
        "type": "Produce",
        "name": "Gabba Fruit Market",
        "address": "86 Annerley Rd, Woolloongabba QLD 4102",
        "saturdayOpenHrs": "7 am-8 pm",
        "sundayOpenHrs": "7 am-8 pm",
        "mondayOpenHrs": "7 am-6 pm",
        "tuesdayOpenHrs": "7 am-8 pm",
        "wednesdaydayOpenHrs": "7 am-8 pm",
        "thrusdayOpenHrs": "7 am-8 pm",
        "fridayOpenHrs": "7 am-8 pm",
        "phone": "(07) 3391 8200",
        "google-reviews": 4.5,
        "website": "https://www.abetterchoice.com.au/stores/gabba-fruit-market/",
        "keywords": ["fruit", "vegetables"],
        "latNLong": [-27.49010855896749, 153.02754856137048]
    },
    {
        "type": "Markets",
        "name": "Saturday Fresh Market, Rocklea",
        "address": "385 Sherwood Rd, Rocklea QLD 4106",
        "saturdayOpenHrs": "6 am-12 pm",
        "sundayOpenHrs": "Closed",
        "mondayOpenHrs": "Closed",
        "tuesdayOpenHrs": "Closed",
        "wednesdaydayOpenHrs": "Closed",
        "thrusdayOpenHrs": "Closed",
        "fridayOpenHrs": "Closed",
        "phone": "(07) 3915 4277",
        "google-reviews": 4.5,
        "website": "https://saturdayfreshmarket.com.au/",
        "keywords": ["markets", "market"],
        "latNLong": [-27.536524261441887, 153.00216446791453]
    },
    {
        "type": "Markets",
        "name": "Global Food Markets",
        "address": "Station Rd, Woodridge QLD 4114",
        "saturdayOpenHrs": "Closed",
        "sundayOpenHrs": "6 am-12 pm",
        "mondayOpenHrs": "Closed",
        "tuesdayOpenHrs": "Closed",
        "wednesdaydayOpenHrs": "Closed",
        "thrusdayOpenHrs": "Closed",
        "fridayOpenHrs": "Closed",
        "phone": "0452 098 670",
        "google-reviews": 4.5,
        "website": "https://globalfoodmarkets.com.au/",
        "keywords": ["markets", "market"],
        "latNLong": [-27.63729570588213, 153.1043430967529]
    },
    {
        "type": "Markets",
        "name": "Jan Powers Farmers Markets Powerhouse",
        "address": "The Brisbane Powerhouse, 119 Lamington St, New Farm QLD 4005",
        "saturdayOpenHrs": "6 am-12 pm",
        "sundayOpenHrs": "Closed",
        "mondayOpenHrs": "Closed",
        "tuesdayOpenHrs": "Closed",
        "wednesdaydayOpenHrs": "Closed",
        "thrusdayOpenHrs": "Closed",
        "fridayOpenHrs": "Closed",
        "phone": "NA",
        "google-reviews": 4.5,
        "website": "https://www.janpowersfarmersmarkets.com.au/",
        "keywords": ["markets", "market"],
        "latNLong": [-27.46854408323546, 153.05397318140663]
    },
    {
        "type": "Markets",
        "name": "Mt Gravatt Sunday Markets",
        "address": "1644 Logan Road Enter via, Broadwater Rd, Mount Gravatt QLD 4122",
        "saturdayOpenHrs": "Closed",
        "sundayOpenHrs": "6 am-12 pm",
        "mondayOpenHrs": "Closed",
        "tuesdayOpenHrs": "Closed",
        "wednesdaydayOpenHrs": "Closed",
        "thrusdayOpenHrs": "Closed",
        "fridayOpenHrs": "Closed",
        "phone": "0419 739 411",
        "google-reviews": 4.5,
        "website": "https://mtgravattmarkets.com/",
        "keywords": ["markets", "market"],
        "latNLong": [-27.544178221015905, 153.0842187679148]
    },
    {
        "type": "Meats",
        "name": "Super Butcher, Eagle Farm",
        "address": "6 Eagleview Pl, Eagle Farm QLD 4009",
        "saturdayOpenHrs": "7 am-5 pm",
        "sundayOpenHrs": "8 am-5 pm",
        "mondayOpenHrs": "8 am-6 pm",
        "tuesdayOpenHrs": "8 am-6 pm",
        "wednesdaydayOpenHrs": "8 am-6 pm",
        "thrusdayOpenHrs": "8 am-6 pm",
        "fridayOpenHrs": "8 am-6 pm",
        "phone": "1300 002 493",
        "google-reviews": 4.5,
        "website": "https://superbutcher.com.au/",
        "keywords": ["butcher", "butchers", "meat"],
        "latNLong": [-27.43610034367169, 153.08554481208714]
    },
    {
        "type": "Meats",
        "name": "Super Butcher, Browns Plains",
        "address": "18 Eastern Rd, Browns Plains QLD 4118",
        "saturdayOpenHrs": "7 am-5 pm",
        "sundayOpenHrs": "8 am-5 pm",
        "mondayOpenHrs": "8 am-6 pm",
        "tuesdayOpenHrs": "8 am-6 pm",
        "wednesdaydayOpenHrs": "8 am-6 pm",
        "thrusdayOpenHrs": "8 am-6 pm",
        "fridayOpenHrs": "8 am-6 pm",
        "phone": "0407 194 956",
        "google-reviews": 4.5,
        "website": "https://superbutcher.com.au/",
        "keywords": ["butcher", "butchers", "meat"],
        "latNLong": [-27.663913079200412, 153.04379405151153]
    },
    {
        "type": "Meats",
        "name": "Super Butcher, Birkdale",
        "address": "180 Birkdale Rd, Birkdale QLD 4159",
        "saturdayOpenHrs": "7 am-5 pm",
        "sundayOpenHrs": "8 am-5 pm",
        "mondayOpenHrs": "8 am-6 pm",
        "tuesdayOpenHrs": "8 am-6 pm",
        "wednesdaydayOpenHrs": "8 am-6 pm",
        "thrusdayOpenHrs": "8 am-6 pm",
        "fridayOpenHrs": "8 am-6 pm",
        "phone": "0400 155 833",
        "google-reviews": 4.5,
        "website": "https://superbutcher.com.au/",
        "keywords": ["butcher", "butchers", "meat"],
        "latNLong": [-27.49190198611973, 153.21733682558352]
    },
    {
        "type": "Meats",
        "name": "Deagon Bulk Meats",
        "address": "116 Barclay St, Deagon QLD 4017",
        "saturdayOpenHrs": "6 am-3 pm",
        "sundayOpenHrs": "8 am-6 pm",
        "mondayOpenHrs": "7 am-1 pm",
        "tuesdayOpenHrs": "6 am-5:30 pm",
        "wednesdaydayOpenHrs": "6 am-5:30 pm",
        "thrusdayOpenHrs": "6 am-5:30 pm",
        "fridayOpenHrs": "6 am-5:30 pm",
        "phone": "(07) 3269 1417",
        "google-reviews": 4.5,
        "website": "https://www.deagonbulkmeats.com.au/",
        "keywords": ["butcher", "butchers", "meat"],
        "latNLong": [-27.32682340363385, 153.0619930544134]
    },
    {
        "type": "Meats",
        "name": "Inghams Factory Outlet, Lytton",
        "address": "86 Trade St, Lytton QLD 4178",
        "saturdayOpenHrs": "8 am - 2 pm",
        "sundayOpenHrs": "Closed",
        "mondayOpenHrs": "8 am-4 pm",
        "tuesdayOpenHrs": "8 am-4 pm",
        "wednesdaydayOpenHrs": "8 am-4 pm",
        "thrusdayOpenHrs": "8 am-4 pm",
        "fridayOpenHrs": "8 am-4 pm",
        "phone": "(07) 3097 2032",
        "google-reviews": 4.5,
        "website": "https://www.facebook.com/InghamsLyttonFactoryOutlet",
        "keywords": ["butcher", "butchers", "meat"],
        "latNLong": [-27.426777607591514, 153.1504541102406]
    },
    {
        "type": "Meats",
        "name": "Rock n Roll Butcher, Greenslopes",
        "address": "500 Logan Rd, Greenslopes QLD 4120",
        "saturdayOpenHrs": "6 am - 4 pm",
        "sundayOpenHrs": "6 am - 4 pm",
        "mondayOpenHrs": "6 am-6 pm",
        "tuesdayOpenHrs": "6 am-6 pm",
        "wednesdaydayOpenHrs": "6 am-6 pm",
        "thrusdayOpenHrs": "6 am-6 pm",
        "fridayOpenHrs": "6 am-6 pm",
        "phone": "(07) 3394 3365",
        "google-reviews": 4.5,
        "website": "https://www.rocknrollbutcher.com.au/",
        "keywords": ["butcher", "butchers", "meat"],
        "latNLong": [-27.500859001631007, 153.0479239030272]
    },
    {
        "type": "Meats",
        "name": "Big Gun Wholesale Meats, Underwood",
        "address": "2912 Logan Rd, Underwood QLD 4119",
        "saturdayOpenHrs": "4 am - 4 pm",
        "sundayOpenHrs": "4 am - 4 pm",
        "mondayOpenHrs": "5 am-5 pm",
        "tuesdayOpenHrs": "5 am-5 pm",
        "wednesdaydayOpenHrs": "5 am-5 pm",
        "thrusdayOpenHrs": "5 am-5 pm",
        "fridayOpenHrs": "5 am-5 pm",
        "phone": "(07) 3341 2033",
        "google-reviews": 3.5,
        "website": "https://www.biggun.com.au/",
        "keywords": ["butcher", "butchers", "meat"],
        "latNLong": [-27.60767267457671, 153.11191816628678]
    },
    {
        "type": "Meats",
        "name": "Ismail’s Discount Halal Meats/ Australian Halal Butcheries",
        "address": "298 Brunswick St, Fortitude Valley QLD 4006",
        "saturdayOpenHrs": "8 am - 4 pm",
        "sundayOpenHrs": "Closed",
        "mondayOpenHrs": "7 am-5 pm",
        "tuesdayOpenHrs": "7 am-5 pm",
        "wednesdaydayOpenHrs": "7 am-5 pm",
        "thrusdayOpenHrs": "7 am-5 pm",
        "fridayOpenHrs": "7 am-5 pm",
        "phone": "(07) 3252 5295",
        "google-reviews": 3.5,
        "website": "https://australianhalalbutcheries.com.au/",
        "keywords": ["butcher", "butchers", "meat"],
        "latNLong": [-27.457205670662578, 153.03477499696737]
    },
    {
        "type": "Fish",
        "name": "Aussie Seafood House, Durack",
        "address": "656 Blunder Rd, Durack QLD 4077",
        "saturdayOpenHrs": "9 am-5:30 pm",
        "sundayOpenHrs": "9 am-4:30 pm",
        "mondayOpenHrs": "9:30 am-5:30 pm",
        "tuesdayOpenHrs": "9:30 am-5:30 pm",
        "wednesdaydayOpenHrs": "9:30 am-5:30 pm",
        "thrusdayOpenHrs": "9:30 am-5:30 pm",
        "fridayOpenHrs": "9:30 am-5:30 pm",
        "phone": "(07) 3279 9400",
        "google-reviews": 4.5,
        "website": "https://aussieseafoodhouse.com.au/",
        "keywords": ["fish"],
        "latNLong": [-27.595616016910913, 152.9880113693148]
    },
    {
        "type": "Fish",
        "name": "Aussie Seafood House, Chandler",
        "address": "3230 Old Cleveland Rd, Chandler QLD 4155",
        "saturdayOpenHrs": "9 am-5:30 pm",
        "sundayOpenHrs": "9 am-5 pm",
        "mondayOpenHrs": "9:30 am-5:30 pm",
        "tuesdayOpenHrs": "9:30 am-5:30 pm",
        "wednesdaydayOpenHrs": "9:30 am-5:30 pm",
        "thrusdayOpenHrs": "9:30 am-5:30 pm",
        "fridayOpenHrs": "9:30 am-5:30 pm",
        "phone": "0732451016",
        "google-reviews": 4.5,
        "website": "https://aussieseafoodhouse.com.au/",
        "keywords": ["fish"],
        "latNLong": [-27.51561625793109, 153.18413151644666]
    },
    {
        "type": "Fish",
        "name": "Aussie Seafood House, Lawnton",
        "address": "1/690 Gympie Rd, Lawnton QLD 4501",
        "saturdayOpenHrs": "9 am-5:30 pm",
        "sundayOpenHrs": "9 am-5 pm",
        "mondayOpenHrs": "9:30 am-5:30 pm",
        "tuesdayOpenHrs": "9:30 am-5:30 pm",
        "wednesdaydayOpenHrs": "9:30 am-5:30 pm",
        "thrusdayOpenHrs": "9:30 am-5:30 pm",
        "fridayOpenHrs": "9:30 am-5:30 pm",
        "phone": "0738810895",
        "google-reviews": 4.5,
        "website": "https://aussieseafoodhouse.com.au/",
        "keywords": ["fish"],
        "latNLong": [-27.288814746450026, 152.98438267830497]
    },
    {
        "type": "Fish",
        "name": "Sunnybank Fish Market",
        "address": "2 Zamia St, Robertson QLD 4109",
        "saturdayOpenHrs": "9 am-5 pm",
        "sundayOpenHrs": "9 am-5:30 pm",
        "mondayOpenHrs": "9:30 am-5:30 pm",
        "tuesdayOpenHrs": "9 am-5:30 pm",
        "wednesdaydayOpenHrs": "9 am-5:30pm",
        "thrusdayOpenHrs": "9 am-5:30pm",
        "fridayOpenHrs": "9 am-5:30pm",
        "phone": "(07) 3344 7788",
        "google-reviews": 4.5,
        "website": "https://www.facebook.com/SunnybankFishMarket/",
        "keywords": ["fish"],
        "latNLong": [-27.57017934284743, 153.06043161164646]
    },
    {
        "type": "Fish",
        "name": "Sumner Seafood 森拿海鮮 since 1988",
        "address": "4/59 Randolph St, Rocklea QLD 4106",
        "saturdayOpenHrs": "9:30 am-3 pm",
        "sundayOpenHrs": "Closed",
        "mondayOpenHrs": "9:30 am-5:30 pm",
        "tuesdayOpenHrs": "9:30 am-4 pm",
        "wednesdaydayOpenHrs": "9:30 am-4 pm",
        "thrusdayOpenHrs": "9:30 am-4 pm",
        "fridayOpenHrs": "9:30 am-4 pm",
        "phone": "(07) 3373 8181",
        "google-reviews": 5,
        "website": "https://sumnerseafood.com.au/",
        "keywords": ["fish"],
        "latNLong": [-27.56201979807324, 152.99870109205568]
    },
    {
        "type": "Fish",
        "name": "Inala Fish Market",
        "address": "Civic Centre, Brisbane, Shop 1/37 Corsair Ave, Inala QLD 4077",
        "saturdayOpenHrs": "7 am-4:30 pm",
        "sundayOpenHrs": "7 am-4:30 pm",
        "mondayOpenHrs": "9:30 am-5:30 pm",
        "tuesdayOpenHrs": "8 am-4:30 pm",
        "wednesdaydayOpenHrs": "8 am-4:30 pm",
        "thrusdayOpenHrs": "8 am-4:30 pm",
        "fridayOpenHrs": "8 am-4:30 pm",
        "phone": "(07) 3279 9799",
        "google-reviews": 4.5,
        "website": "https://www.facebook.com/Inala-Fish-Market-167104750302964/",
        "keywords": ["fish"],
        "latNLong": [-27.59968866488319, 152.97393794115015]
    }
]

